odoo/addons/purchase_sale_inter_company/README.rst
odoo/addons/purchase_sale_inter_company/__init__.py
odoo/addons/purchase_sale_inter_company/__manifest__.py
odoo/addons/purchase_sale_inter_company/demo/res_partner_demo.xml
odoo/addons/purchase_sale_inter_company/i18n/de.po
odoo/addons/purchase_sale_inter_company/i18n/es.po
odoo/addons/purchase_sale_inter_company/i18n/fr.po
odoo/addons/purchase_sale_inter_company/i18n/fr_FR.po
odoo/addons/purchase_sale_inter_company/i18n/it.po
odoo/addons/purchase_sale_inter_company/i18n/purchase_sale_inter_company.pot
odoo/addons/purchase_sale_inter_company/i18n/sl.po
odoo/addons/purchase_sale_inter_company/i18n/zh_CN.po
odoo/addons/purchase_sale_inter_company/models/__init__.py
odoo/addons/purchase_sale_inter_company/models/account_move.py
odoo/addons/purchase_sale_inter_company/models/purchase_order.py
odoo/addons/purchase_sale_inter_company/models/res_company.py
odoo/addons/purchase_sale_inter_company/models/res_config.py
odoo/addons/purchase_sale_inter_company/models/sale_order.py
odoo/addons/purchase_sale_inter_company/models/stock_move.py
odoo/addons/purchase_sale_inter_company/models/stock_picking.py
odoo/addons/purchase_sale_inter_company/readme/CONFIGURATION.rst
odoo/addons/purchase_sale_inter_company/readme/CONTEXT.rst
odoo/addons/purchase_sale_inter_company/readme/CONTRIBUTORS.rst
odoo/addons/purchase_sale_inter_company/readme/DESCRIPTION.rst
odoo/addons/purchase_sale_inter_company/readme/ROADMAP.rst
odoo/addons/purchase_sale_inter_company/readme/USAGE.rst
odoo/addons/purchase_sale_inter_company/static/description/icon.png
odoo/addons/purchase_sale_inter_company/static/description/index.html
odoo/addons/purchase_sale_inter_company/tests/__init__.py
odoo/addons/purchase_sale_inter_company/tests/test_inter_company_purchase_sale.py
odoo/addons/purchase_sale_inter_company/views/res_config_view.xml
odoo/addons/purchase_sale_inter_company/wizard/__init__.py
odoo14_addon_purchase_sale_inter_company-14.0.2.4.1.dist-info/METADATA
odoo14_addon_purchase_sale_inter_company-14.0.2.4.1.dist-info/WHEEL
odoo14_addon_purchase_sale_inter_company-14.0.2.4.1.dist-info/top_level.txt
odoo14_addon_purchase_sale_inter_company-14.0.2.4.1.dist-info/RECORD
